azul_bedrock/__init__.py
azul_bedrock/dispatcher.py
azul_bedrock/dispatcher_params.py
azul_bedrock/exceptions.py
azul_bedrock/identify.py
azul_bedrock/identify.yaml
azul_bedrock/models_api.py
azul_bedrock/models_auth.py
azul_bedrock/models_network.py
azul_bedrock/models_settings.py
azul_bedrock/trusted_mime.yaml
azul_bedrock/yara_rules.yar
azul_bedrock/mock/__init__.py
azul_bedrock/mock/dp.py
azul_bedrock/mock/events.py
azul_bedrock/mock/helper.py
azul_bedrock/mock/state.py
azul_bedrock/mock/streams.py
azul_bedrock/models_restapi/__init__.py
azul_bedrock/models_restapi/basic.py
azul_bedrock/models_restapi/binaries.py
azul_bedrock/models_restapi/binaries_auto_complete.py
azul_bedrock/models_restapi/binaries_data.py
azul_bedrock/models_restapi/features.py
azul_bedrock/models_restapi/plugins.py
azul_bedrock/models_restapi/purge.py
azul_bedrock/models_restapi/sources.py
azul_bedrock/models_restapi/statistics.py
azul_bedrock/test_utils/bucket_storage.py
azul_bedrock/test_utils/errors.py
azul_bedrock/test_utils/file_manager.py
azul_bedrock/test_utils/file_manager_settings.py
azul_bedrock-9.0.32.dist-info/METADATA
azul_bedrock-9.0.32.dist-info/WHEEL
azul_bedrock-9.0.32.dist-info/top_level.txt
azul_bedrock-9.0.32.dist-info/RECORD
