Metadata-Version: 2.4
Name: azul-bedrock
Version: 9.0.32
Summary: Shared library for Azul models and operations.
Home-page: https://www.asd.gov.au/
Author: Azul
Author-email: azul@asd.gov.au
Classifier: Development Status :: 5 - Production/Stable
Classifier: License :: OSI Approved :: MIT License
Classifier: Programming Language :: Python
Classifier: Programming Language :: Python :: 3
Classifier: Programming Language :: Python :: 3.12
Classifier: Programming Language :: Python :: 3.13
Classifier: Programming Language :: Python :: 3.14
Classifier: Intended Audience :: Developers
Classifier: Topic :: Software Development :: Libraries
Requires-Python: >=3.12
Requires-Dist: cachetools
Requires-Dist: fastapi
Requires-Dist: httpx
Requires-Dist: multipart
Requires-Dist: pendulum
Requires-Dist: pydantic
Requires-Dist: python-magic>=0.4.15
Requires-Dist: pyyaml
Requires-Dist: starlette
Requires-Dist: yara-python
Provides-Extra: mock
Requires-Dist: cart; extra == "mock"
Requires-Dist: fastapi[all]>=0.60.0; extra == "mock"
Requires-Dist: azure-storage-blob; extra == "mock"
Requires-Dist: pytest; extra == "mock"
Requires-Dist: tox; extra == "mock"
Requires-Dist: urllib3; extra == "mock"
Provides-Extra: test-utils
Requires-Dist: cart; extra == "test-utils"
Requires-Dist: fastapi[all]>=0.60.0; extra == "test-utils"
Requires-Dist: azure-storage-blob; extra == "test-utils"
Requires-Dist: pytest; extra == "test-utils"
Requires-Dist: tox; extra == "test-utils"
Requires-Dist: urllib3; extra == "test-utils"
Dynamic: author
Dynamic: author-email
Dynamic: classifier
Dynamic: description
Dynamic: description-content-type
Dynamic: home-page
Dynamic: provides-extra
Dynamic: requires-dist
Dynamic: requires-python
Dynamic: summary
